pykevoplus/__init__.py
pykevoplus-1.0.1.dist-info/DESCRIPTION.rst
pykevoplus-1.0.1.dist-info/METADATA
pykevoplus-1.0.1.dist-info/RECORD
pykevoplus-1.0.1.dist-info/WHEEL
pykevoplus-1.0.1.dist-info/metadata.json
pykevoplus-1.0.1.dist-info/top_level.txt
