Metadata-Version: 2.0
Name: pykevoplus
Version: 1.0.1
Summary: Control Kwikset Kevo locks
Home-page: https://github.com/cseelye/pykevoplus
Author: Carl Seelye
Author-email: cseelye@gmail.com
License: MIT
Keywords: kevo kwikset
Platform: UNKNOWN
Requires-Dist: beautifulsoup4
Requires-Dist: requests
